instr/__init__.py
instr/agilent34410a.py
instr/agilent34410amock.py
instr/agilentN5230A.py
instr/agilente3644a.py
instr/agilente3644amock.py
instr/agilente8362b.py
instr/agilente8362bmock.py
instr/agilentn1914a.py
instr/agilentn1914amock.py
instr/agilentn5183a.py
instr/agilentn5183amock.py
instr/agilentn9030a.py
instr/agilentn9030amock.py
instr/instrumentfactory.py
instr/obzor304.py
instr/obzor304mock.py
instr/oscilloscope.py
instr/oscilloscopemock.py
instr/pna20.py
instr/pna20mock.py
instr/semiconductoranalyzer.py
instr/semiconductoranalyzermock.py
instr-0.0.1.dist-info/METADATA
instr-0.0.1.dist-info/WHEEL
instr-0.0.1.dist-info/top_level.txt
instr-0.0.1.dist-info/RECORD
